LICENSE
eslogger.py
events.py
cbpcommon.egg-info/PKG-INFO
cbpcommon.egg-info/SOURCES.txt
cbpcommon.egg-info/dependency_links.txt
cbpcommon.egg-info/requires.txt
cbpcommon.egg-info/top_level.txt
cbpcommon-0.0.17.dist-info/LICENSE
cbpcommon-0.0.17.dist-info/METADATA
cbpcommon-0.0.17.dist-info/WHEEL
cbpcommon-0.0.17.dist-info/top_level.txt
cbpcommon-0.0.17.dist-info/RECORD
