Metadata-Version: 2.1
Name: cbpcommon
Version: 0.0.17
Summary: Common library for Crypto Bot Platform
Home-page: https://github.com/Crypto-Bot-Platform/cbpcommon
Author: Boris Tsekinovsky
Author-email: t.boris@gmail.com
License: MIT
Platform: UNKNOWN
License-File: LICENSE
Requires-Dist: avro (==1.11.0)
Requires-Dist: confluent-kafka (==1.8.2)
Requires-Dist: setuptools (>=60.9.0)
Requires-Dist: elasticsearch (~=7.16.3)
Requires-Dist: jsonpickle
